{
    "key": "independence",
    "items": [
        51483000,
        51484000,
        51485000,
        51486000,
        51487000,
        51488000,
        51489000,
        51490000,
        51491000,
        51492000,
        51493000,
        51494000,
        51495000,
        51496000,
        51497000,
        51498000,
        51499000,
        51500000,
        51501000,
        51502000,
        51503000,
        51504000,
        51505000,
        51506000,
        51507000,
        51508000,
        51509000,
        51510000,
        51511000,
        51512000,
        51513000,
        51514000,
        51515000,
        51516000,
        51517000,
        51518000,
        51519000,
        51520000,
        51521000,
        51522000,
        51523000,
        51524000,
        51525000,
        51526000,
        51527000,
        51528000,
        51529000,
        51530000,
        51531000,
        51532000,
        51533000,
        51534000,
        51535000,
        51536000,
        51537000,
        51538000,
        51539000,
        51540000,
        51541000,
        51542000,
        51543000
    ],
    "sets": [
        "independence_day_2019_set_1",
        "independence_day_2019_set_2",
        "independence_day_2019_set_3",
        "independence_day_2019_set_4",
        "independence_day_2019_set_5",
        "independence_day_2019_set_6",
        "independence_day_2019_set_7",
        "independence_day_2019_set_8",
        "independence_day_2019_set_9",
        "independence_day_2019_set_10",
        "independence_day_2019_set_11"
    ],
    "from": "2019-07-04 11:00:00",
    "to": "2019-07-25 23:59:59",
    "year": 2019,
    "quests": [206],
    "tombola": 24,
    "beta_from": "2019-06-19 11:00:00",
    "beta_to": "2019-07-18 23:59:59",
    "forum_url": "https://forum.beta.the-west.net/index.php?threads/independence-day-2019.3437/"
}
